thalamus_serve/__init__.py
thalamus_serve/config.py
thalamus_serve/testing.py
thalamus_serve/utils.py
thalamus_serve/core/app.py
thalamus_serve/core/middleware.py
thalamus_serve/core/model.py
thalamus_serve/core/routes.py
thalamus_serve/infra/cache.py
thalamus_serve/infra/gpu.py
thalamus_serve/observability/logging.py
thalamus_serve/observability/metrics.py
thalamus_serve/observability/middleware.py
thalamus_serve/schemas/api.py
thalamus_serve/schemas/common.py
thalamus_serve/schemas/storage.py
thalamus_serve/storage/fetch.py
thalamus_serve/tests/conftest.py
thalamus_serve/tests/test_service_contract.py
thalamus_serve-0.2.0.dist-info/METADATA
thalamus_serve-0.2.0.dist-info/WHEEL
thalamus_serve-0.2.0.dist-info/licenses/LICENSE
thalamus_serve-0.2.0.dist-info/RECORD
