Metadata-Version: 2.4
Name: thalamus-serve
Version: 0.2.0
Summary: A Python ML model serving framework with built-in observability, caching, and GPU management
Project-URL: Homepage, https://github.com/brick-so/thalamus-serve
Project-URL: Documentation, https://github.com/brick-so/thalamus-serve#readme
Project-URL: Repository, https://github.com/brick-so/thalamus-serve
Project-URL: Issues, https://github.com/brick-so/thalamus-serve/issues
Project-URL: Changelog, https://github.com/brick-so/thalamus-serve/blob/main/CHANGELOG.md
Author: Brick Technologies LLC
License-Expression: Apache-2.0
License-File: LICENSE
Keywords: api,cuda,fastapi,gpu,huggingface,inference,machine-learning,ml-serving,model-serving,observability,prometheus,pytorch
Classifier: Development Status :: 4 - Beta
Classifier: Framework :: FastAPI
Classifier: Intended Audience :: Developers
Classifier: Intended Audience :: Science/Research
Classifier: License :: OSI Approved :: Apache Software License
Classifier: Operating System :: OS Independent
Classifier: Programming Language :: Python :: 3
Classifier: Programming Language :: Python :: 3.10
Classifier: Programming Language :: Python :: 3.11
Classifier: Programming Language :: Python :: 3.12
Classifier: Topic :: Internet :: WWW/HTTP :: HTTP Servers
Classifier: Topic :: Scientific/Engineering :: Artificial Intelligence
Classifier: Typing :: Typed
Requires-Python: >=3.10
Requires-Dist: boto3>=1.42.27
Requires-Dist: fastapi>=0.115.0
Requires-Dist: httpx>=0.28.1
Requires-Dist: huggingface-hub>=0.20.0
Requires-Dist: packaging>=24.0
Requires-Dist: prometheus-client>=0.20.0
Requires-Dist: pydantic>=2.10.0
Requires-Dist: structlog>=24.0.0
Requires-Dist: uvicorn>=0.30.0
Provides-Extra: all
Requires-Dist: boto3-stubs>=1.42.0; extra == 'all'
Requires-Dist: mypy>=1.10.0; extra == 'all'
Requires-Dist: pytest-cov>=4.1.0; extra == 'all'
Requires-Dist: pytest>=8.0.0; extra == 'all'
Requires-Dist: ruff>=0.4.0; extra == 'all'
Requires-Dist: torch>=2.0.0; extra == 'all'
Requires-Dist: twine>=5.0.0; extra == 'all'
Provides-Extra: dev
Requires-Dist: boto3-stubs>=1.42.0; extra == 'dev'
Requires-Dist: mypy>=1.10.0; extra == 'dev'
Requires-Dist: pytest-cov>=4.1.0; extra == 'dev'
Requires-Dist: pytest>=8.0.0; extra == 'dev'
Requires-Dist: ruff>=0.4.0; extra == 'dev'
Requires-Dist: twine>=5.0.0; extra == 'dev'
Provides-Extra: gpu
Requires-Dist: torch>=2.0.0; extra == 'gpu'
